tests/__init__.py
tseopt/__init__.py
tseopt/data_source/__init__.py
tseopt/data_source/mercantile_exchange/__init__.py
tseopt/data_source/mercantile_exchange/api.py
tseopt/data_source/mercantile_exchange/descriptor.py
tseopt/data_source/mercantile_exchange/schema.py
tseopt/data_source/tadbir/__init__.py
tseopt/data_source/tadbir/api.py
tseopt/data_source/tadbir/schema.py
tseopt/data_source/tsetmc/__init__.py
tseopt/data_source/tsetmc/api.py
tseopt/data_source/tsetmc/schema.py
tseopt/data_source/tsetmc/limit_order_book/__init__.py
tseopt/data_source/tsetmc/limit_order_book/api.py
tseopt/data_source/tsetmc/limit_order_book/schemas.py
tseopt/use_case/__init__.py
tseopt/use_case/options_chains.py
tseopt/use_case/screen_market.py
tseopt-0.1.5.dist-info/LICENSE
tseopt-0.1.5.dist-info/METADATA
tseopt-0.1.5.dist-info/WHEEL
tseopt-0.1.5.dist-info/top_level.txt
tseopt-0.1.5.dist-info/RECORD
