Metadata-Version: 2.2
Name: tseopt
Version: 0.1.5
Summary: This library contains code for fetching and processing option data from the Tehran Stock Exchange using various public APIs.
Home-page: https://github.com/masoudghah/TSELiveOptionData
Author: Masoud Ghahremani
Author-email: p.masoud.ghahremani@gmail.com
License: MIT
Keywords: tse options tehran derivative
Classifier: Programming Language :: Python :: 3
Classifier: License :: OSI Approved :: MIT License
Classifier: Operating System :: OS Independent
Requires-Python: >=3.12
License-File: LICENSE
Requires-Dist: pandas>=2.2.2
Requires-Dist: requests>=2.32.3
Requires-Dist: fake-useragent==1.5.1
Requires-Dist: jdatetime==5.1.0
Dynamic: author
Dynamic: author-email
Dynamic: classifier
Dynamic: description
Dynamic: description-content-type
Dynamic: home-page
Dynamic: keywords
Dynamic: license
Dynamic: requires-dist
Dynamic: requires-python
Dynamic: summary
